projectkiwi3/Client.py
projectkiwi3/__init__.py
projectkiwi3/models.py
projectkiwi3/utils.py
projectkiwi3-0.1.7.dist-info/LICENSE
projectkiwi3-0.1.7.dist-info/METADATA
projectkiwi3-0.1.7.dist-info/WHEEL
projectkiwi3-0.1.7.dist-info/top_level.txt
projectkiwi3-0.1.7.dist-info/RECORD
