Metadata-Version: 2.1
Name: projectkiwi3
Version: 0.1.7
Summary: This module is a means for interfacing with projectkiwi.io using python.
Author-email: Michael Thoreau <michael@projectkiwi.io>
License-File: LICENSE
Requires-Dist: requests
Requires-Dist: pydantic
Requires-Dist: numpy
Requires-Dist: pillow
Requires-Dist: shapely
